qudi/default.cfg
qudi/gui/camera/camera_settings_dialog.py
qudi/gui/camera/cameragui.py
qudi/gui/laser/laser_control_dockwidget.py
qudi/gui/laser/laser_gui.py
qudi/gui/laser/laser_plot_dockwidgets.py
qudi/gui/laserscanner/laserscannergui.py
qudi/gui/nv_calculator/nv_calculatorgui.py
qudi/gui/nv_calculator/ui_nv_calculator.ui
qudi/gui/odmr/odmr_control_dockwidget.py
qudi/gui/odmr/odmr_fit_dockwidget.py
qudi/gui/odmr/odmr_main_window.py
qudi/gui/odmr/odmr_plot_widget.py
qudi/gui/odmr/odmr_settings_dialog.py
qudi/gui/odmr/odmrgui.py
qudi/gui/pidgui/pidgui.py
qudi/gui/pidgui/ui_pid_control.ui
qudi/gui/poimanager/poimanagergui.py
qudi/gui/poimanager/ui_poimanagergui.ui
qudi/gui/poimanager/ui_reorient_roi_dialog.ui
qudi/gui/pulsed/pulse_editors.py
qudi/gui/pulsed/pulsed_custom_widgets.py
qudi/gui/pulsed/pulsed_item_delegates.py
qudi/gui/pulsed/pulsed_maingui.py
qudi/gui/pulsed/ui_predefined_methods.ui
qudi/gui/pulsed/ui_predefined_methods_config.ui
qudi/gui/pulsed/ui_pulse_analysis.ui
qudi/gui/pulsed/ui_pulse_editor.ui
qudi/gui/pulsed/ui_pulse_extraction.ui
qudi/gui/pulsed/ui_pulsed_main_gui_settings_analysis.ui
qudi/gui/pulsed/ui_pulsed_main_gui_settings_generator.ui
qudi/gui/pulsed/ui_pulsed_maingui.ui
qudi/gui/pulsed/ui_sequence_editor.ui
qudi/gui/qdplot/main_window.py
qudi/gui/qdplot/plot_widget.py
qudi/gui/qdplot/qdplot_gui.py
qudi/gui/scanning/axes_control_dockwidget.py
qudi/gui/scanning/optimizer_dockwidget.py
qudi/gui/scanning/optimizer_setting_dialog.py
qudi/gui/scanning/scan_dockwidget.py
qudi/gui/scanning/scan_settings_dialog.py
qudi/gui/scanning/scan_widget.py
qudi/gui/scanning/scannergui.py
qudi/gui/scanning/tilt_correction_dockwidget.py
qudi/gui/scanning/ui_scannergui.ui
qudi/gui/spectrometer/control_widget.py
qudi/gui/spectrometer/data_widget.py
qudi/gui/spectrometer/settingsdialog.py
qudi/gui/spectrometer/spectrometer_gui.py
qudi/gui/spectrometer/spectrometer_window.py
qudi/gui/switch/switch_gui.py
qudi/gui/switch/switch_state_widgets.py
qudi_iqo_modules-0.6.0.dist-info/licenses/AUTHORS.md
qudi_iqo_modules-0.6.0.dist-info/licenses/LICENSE
qudi_iqo_modules-0.6.0.dist-info/licenses/LICENSE.LESSER
qudi_iqo_modules-0.6.0.dist-info/METADATA
qudi_iqo_modules-0.6.0.dist-info/WHEEL
qudi_iqo_modules-0.6.0.dist-info/top_level.txt
qudi_iqo_modules-0.6.0.dist-info/RECORD
