Metadata-Version: 2.4
Name: qudi-iqo-modules
Version: 0.6.0
Summary: IQO measurement modules collection for qudi
Project-URL: Homepage, https://github.com/Ulm-IQO/qudi-iqo-modules
Project-URL: Repository, https://github.com/Ulm-IQO/qudi-iqo-modules.git
Project-URL: Bug Tracker, https://github.com/Ulm-IQO/qudi-iqo-modules/issues
Project-URL: Changelog, https://github.com/Ulm-IQO/qudi-iqo-modules/blob/main/docs/changelog.md
Keywords: qudi,diamond,quantum,confocal,experiment,lab,laboratory,instrumentation,instrument,modular,measurement
Classifier: Development Status :: 5 - Production/Stable
Classifier: Environment :: Win32 (MS Windows)
Classifier: Environment :: X11 Applications
Classifier: Environment :: MacOS X
Classifier: Intended Audience :: Science/Research
Classifier: Intended Audience :: End Users/Desktop
Classifier: License :: OSI Approved :: GNU Lesser General Public License v3 (LGPLv3)
Classifier: Natural Language :: English
Classifier: Operating System :: Microsoft :: Windows :: Windows 8
Classifier: Operating System :: Microsoft :: Windows :: Windows 8.1
Classifier: Operating System :: Microsoft :: Windows :: Windows 10
Classifier: Operating System :: Microsoft :: Windows :: Windows 11
Classifier: Operating System :: MacOS :: MacOS X
Classifier: Operating System :: Unix
Classifier: Operating System :: POSIX :: Linux
Classifier: Programming Language :: Python :: 3.8
Classifier: Programming Language :: Python :: 3.9
Classifier: Programming Language :: Python :: 3.10
Classifier: Topic :: Scientific/Engineering
Requires-Python: <3.11,>=3.8
License-File: LICENSE
License-File: LICENSE.LESSER
License-File: AUTHORS.md
Requires-Dist: qudi-core==1.6.0
Requires-Dist: entrypoints==0.4
Requires-Dist: fysom==2.1.6
Requires-Dist: lmfit==1.3.2
Requires-Dist: lxml==5.3.0
Requires-Dist: matplotlib==3.7.5
Requires-Dist: nidaqmx==1.0.2
Requires-Dist: numpy<2.0,==1.24.4
Requires-Dist: pyqtgraph==0.13.3
Requires-Dist: PySide2
Requires-Dist: PyVisa==1.14.1
Requires-Dist: scipy==1.10.1
Requires-Dist: zaber_motion==7.2.3
Provides-Extra: dev-test
Requires-Dist: pytest; extra == "dev-test"
Requires-Dist: pytest-qt; extra == "dev-test"
Requires-Dist: coverage; extra == "dev-test"
Dynamic: license-file
